[{"__type__":"cc.SpriteFrame","content":{"name":"11110100","texture":"66u4n4WGFMRq+xitnAETaF","rect":[196,66,64,64],"offset":[0,0],"originalSize":[64,64]}},{"__type__":"cc.SpriteFrame","content":{"name":"00001001","texture":"66u4n4WGFMRq+xitnAETaF","rect":[196,196,64,64],"offset":[0,0],"originalSize":[64,64]}},{"__type__":"cc.SpriteFrame","content":{"name":"00101110","texture":"66u4n4WGFMRq+xitnAETaF","rect":[131,261,64,64],"offset":[0,0],"originalSize":[64,64]}},{"__type__":"cc.SpriteFrame","content":{"name":"11010001","texture":"66u4n4WGFMRq+xitnAETaF","rect":[391,1,64,64],"offset":[0,0],"originalSize":[64,64]}},{"__type__":"cc.SpriteFrame","content":{"name":"00100000","texture":"66u4n4WGFMRq+xitnAETaF","rect":[261,196,64,64],"offset":[0,0],"originalSize":[64,64]}},{"__type__":"cc.SpriteFrame","content":{"name":"11111001","texture":"66u4n4WGFMRq+xitnAETaF","rect":[1,261,64,64],"offset":[0,0],"originalSize":[64,64]}},{"__type__":"cc.SpriteFrame","content":{"name":"00010110","texture":"66u4n4WGFMRq+xitnAETaF","rect":[261,131,64,64],"offset":[0,0],"originalSize":[64,64]}},{"__type__":"cc.SpriteFrame","content":{"name":"01101011","texture":"66u4n4WGFMRq+xitnAETaF","rect":[326,66,64,64],"offset":[0,0],"originalSize":[64,64]}},{"__type__":"cc.SpriteFrame","content":{"name":"01101000","texture":"66u4n4WGFMRq+xitnAETaF","rect":[391,66,64,64],"offset":[0,0],"originalSize":[64,64]}},{"__type__":"cc.SpriteFrame","content":{"name":"10000000","texture":"66u4n4WGFMRq+xitnAETaF","rect":[261,196,64,64],"offset":[0,0],"originalSize":[64,64]}},{"__type__":"cc.SpriteFrame","content":{"name":"01100000","texture":"66u4n4WGFMRq+xitnAETaF","rect":[131,131,64,64],"offset":[0,0],"originalSize":[64,64]}},{"__type__":"cc.SpriteFrame","content":{"name":"00010100","texture":"66u4n4WGFMRq+xitnAETaF","rect":[326,131,64,64],"offset":[0,0],"originalSize":[64,64]}},{"__type__":"cc.SpriteFrame","content":{"name":"00110110","texture":"66u4n4WGFMRq+xitnAETaF","rect":[261,131,64,64],"offset":[0,0],"originalSize":[64,64]}},{"__type__":"cc.SpriteFrame","content":{"name":"00000011","texture":"66u4n4WGFMRq+xitnAETaF","rect":[196,391,64,64],"offset":[0,0],"originalSize":[64,64]}},{"__type__":"cc.SpriteFrame","content":{"name":"11001001","texture":"66u4n4WGFMRq+xitnAETaF","rect":[66,66,64,64],"offset":[0,0],"originalSize":[64,64]}},{"__type__":"cc.SpriteFrame","content":{"name":"00000100","texture":"66u4n4WGFMRq+xitnAETaF","rect":[261,196,64,64],"offset":[0,0],"originalSize":[64,64]}},{"__type__":"cc.SpriteFrame","content":{"name":"11101011","texture":"66u4n4WGFMRq+xitnAETaF","rect":[66,1,64,64],"offset":[0,0],"originalSize":[64,64]}},{"__type__":"cc.SpriteFrame","content":{"name":"00011111","texture":"66u4n4WGFMRq+xitnAETaF","rect":[196,131,64,64],"offset":[0,0],"originalSize":[64,64]}},{"__type__":"cc.SpriteFrame","content":{"name":"11010000","texture":"66u4n4WGFMRq+xitnAETaF","rect":[391,1,64,64],"offset":[0,0],"originalSize":[64,64]}},{"__type__":"cc.SpriteFrame","content":{"name":"11010111","texture":"66u4n4WGFMRq+xitnAETaF","rect":[261,1,64,64],"offset":[0,0],"originalSize":[64,64]}},{"__type__":"cc.SpriteFrame","content":{"name":"10010111","texture":"66u4n4WGFMRq+xitnAETaF","rect":[66,326,64,64],"offset":[0,0],"originalSize":[64,64]}},{"__type__":"cc.SpriteFrame","content":{"name":"00101111","texture":"66u4n4WGFMRq+xitnAETaF","rect":[131,261,64,64],"offset":[0,0],"originalSize":[64,64]}},{"__type__":"cc.SpriteFrame","content":{"name":"01111111","texture":"66u4n4WGFMRq+xitnAETaF","rect":[131,66,64,64],"offset":[0,0],"originalSize":[64,64]}},{"__type__":"cc.SpriteFrame","content":{"name":"01110100","texture":"66u4n4WGFMRq+xitnAETaF","rect":[196,66,64,64],"offset":[0,0],"originalSize":[64,64]}},{"__type__":"cc.SpriteFrame","content":{"name":"00000000","texture":"66u4n4WGFMRq+xitnAETaF","rect":[261,196,64,64],"offset":[0,0],"originalSize":[64,64]}},{"__type__":"cc.SpriteFrame","content":{"name":"10001011","texture":"66u4n4WGFMRq+xitnAETaF","rect":[391,131,64,64],"offset":[0,0],"originalSize":[64,64]}},{"__type__":"cc.SpriteFrame","content":{"name":"11111000","texture":"66u4n4WGFMRq+xitnAETaF","rect":[1,326,64,64],"offset":[0,0],"originalSize":[64,64]}},{"__type__":"cc.SpriteFrame","content":{"name":"00000111","texture":"66u4n4WGFMRq+xitnAETaF","rect":[196,261,64,64],"offset":[0,0],"originalSize":[64,64]}},{"__type__":"cc.SpriteFrame","content":{"name":"11000000","texture":"66u4n4WGFMRq+xitnAETaF","rect":[66,131,64,64],"offset":[0,0],"originalSize":[64,64]}},{"__type__":"cc.SpriteFrame","content":{"name":"00101001","texture":"66u4n4WGFMRq+xitnAETaF","rect":[131,326,64,64],"offset":[0,0],"originalSize":[64,64]}},{"__type__":"cc.SpriteFrame","content":{"name":"00101000","texture":"66u4n4WGFMRq+xitnAETaF","rect":[131,391,64,64],"offset":[0,0],"originalSize":[64,64]}},{"__type__":"cc.SpriteFrame","content":{"name":"00000110","texture":"66u4n4WGFMRq+xitnAETaF","rect":[196,326,64,64],"offset":[0,0],"originalSize":[64,64]}},{"__type__":"cc.SpriteFrame","content":{"name":"11111111","texture":"66u4n4WGFMRq+xitnAETaF","rect":[1,1,64,64],"offset":[0,0],"originalSize":[64,64]}},{"__type__":"cc.SpriteFrame","content":{"name":"11111011","texture":"66u4n4WGFMRq+xitnAETaF","rect":[1,196,64,64],"offset":[0,0],"originalSize":[64,64]}},{"__type__":"cc.SpriteFrame","content":{"name":"10010100","texture":"66u4n4WGFMRq+xitnAETaF","rect":[66,261,64,64],"offset":[0,0],"originalSize":[64,64]}},{"__type__":"cc.SpriteFrame","content":{"name":"11011111","texture":"66u4n4WGFMRq+xitnAETaF","rect":[196,1,64,64],"offset":[0,0],"originalSize":[64,64]}},{"__type__":"cc.SpriteFrame","content":{"name":"00111111","texture":"66u4n4WGFMRq+xitnAETaF","rect":[131,196,64,64],"offset":[0,0],"originalSize":[64,64]}},{"__type__":"cc.SpriteAtlas","_name":"map_grass_water.plist","_spriteFrames":{"10000000":{"__uuid__":"354JqdFVJGjZgZ4c6dLT/K"},"10001011":{"__uuid__":"8a3N08fSBEbIxEHehDl1Dd"},"10010000":{"__uuid__":"fcSyEhuz9Bkb6MBjeEkIXA"},"10010011":{"__uuid__":"ffwX4gcUBDdqQDTmePzVYO"},"10010100":{"__uuid__":"b64pdW5/BB8LfByS+l+xc+"},"10010111":{"__uuid__":"72JVCIuDxIq4zknF1W2m1a"},"10011111":{"__uuid__":"f095v7zKpMm4bgUFaw2DvX"},"11000000":{"__uuid__":"9bRtPyThpJwrCr/XDYU9TN"},"11001001":{"__uuid__":"5bb5asP0hKBIqxliTFtebW"},"11010000":{"__uuid__":"68D6EzYRhGN7jmJzrRrfCP"},"11010001":{"__uuid__":"24QExt7CNJwoBqbAR1kAYj"},"11010110":{"__uuid__":"fdnIMVmxFLaJpNRXhlVf/u"},"11010111":{"__uuid__":"6ek6s5zyRKHoakiw+glX+s"},"11011111":{"__uuid__":"b7KhLHWflFUJEAlRR2Ov7l"},"11100000":{"__uuid__":"c10sG8eqBFGKwcvv8y8d16"},"11101001":{"__uuid__":"f2xjJOm8hPC7oKbA2cwq6g"},"11101011":{"__uuid__":"5fr2uRJvhACbHQNtTR2T6e"},"11110100":{"__uuid__":"00cVStgFBLR4+PldRu2dLs"},"11110110":{"__uuid__":"d7X2BzC3hG1oIlmPhq/luK"},"11111000":{"__uuid__":"8eFMPtCWJCaLFDpKKFXa+S"},"11111001":{"__uuid__":"26frioPhVLeJvbQdDJI3V3"},"11111011":{"__uuid__":"adCi60fwBORqzkHIO22bAh"},"11111100":{"__uuid__":"f40lFkqWhKprgNISAL87Hw"},"11111110":{"__uuid__":"ffxyskGmZLSqRSMHyy2oU+"},"11111111":{"__uuid__":"acefK2QxZAb4DBU8ulb6Vb"},"00000000":{"__uuid__":"8aRvmjBmpNe4pKq6tAD2LN"},"00000001":{"__uuid__":"e9hJm3gmFKZru5vO5Vypft"},"00000011":{"__uuid__":"56aOg9RrhJMYIySDcfuD+y"},"00000100":{"__uuid__":"5dVW0yif1EhIqVq3O6nVaf"},"00000110":{"__uuid__":"a5AAiJ4jRDjabQa7EXQkny"},"00000111":{"__uuid__":"8fnKQIrWpETIj/82QGbioY"},"00001001":{"__uuid__":"07v9BzadJEF6+S0vcmAc/c"},"00001011":{"__uuid__":"ddYOtA5Z5D2bIkKz9eVvp4"},"00010100":{"__uuid__":"43cNbFBRBDg4icVsYbZ800"},"00010110":{"__uuid__":"27aINRy5xPTbaL51LJUyue"},"00011111":{"__uuid__":"61ZyC9a9pN7YaMxNhvqHAM"},"00100000":{"__uuid__":"24rRgVCzFHGrn5MQwFHN31"},"00101000":{"__uuid__":"a0jv/vImBOsLYLdFEnvoAf"},"00101001":{"__uuid__":"9ctLu9KC9ALJvRs9n/FZMb"},"00101110":{"__uuid__":"1czyj0fS5Fu6MGK8Er1jW6"},"00101111":{"__uuid__":"84eqlg8ztNUIuGNmb+jZ0M"},"00110110":{"__uuid__":"4dSn1r8rNNFLpHpflCyrYn"},"00111111":{"__uuid__":"bcu04RWMRK/KccFOiYLCJl"},"01100000":{"__uuid__":"41C+nDHMBAgIK+M40/ufqe"},"01101000":{"__uuid__":"30M7cWp3pMHK+x1ST3J2Jo"},"01101011":{"__uuid__":"2a28SzhMtB5ZuIPkiPpVJC"},"01101100":{"__uuid__":"f4yvUVM5pMI6YC31/PDgW2"},"01101111":{"__uuid__":"f1B8oAHoNKOK0sCSsUTG7A"},"01110100":{"__uuid__":"8aJhfsRBBEO5c1RVTaR9NV"},"01111111":{"__uuid__":"86ISAFVghLtpqQttRToeZh"}}},{"__type__":"cc.SpriteFrame","content":{"name":"11100000","texture":"66u4n4WGFMRq+xitnAETaF","rect":[131,1,64,64],"offset":[0,0],"originalSize":[64,64]}},{"__type__":"cc.SpriteFrame","content":{"name":"11110110","texture":"66u4n4WGFMRq+xitnAETaF","rect":[1,391,64,64],"offset":[0,0],"originalSize":[64,64]}},{"__type__":"cc.SpriteFrame","content":{"name":"00001011","texture":"66u4n4WGFMRq+xitnAETaF","rect":[391,131,64,64],"offset":[0,0],"originalSize":[64,64]}},{"__type__":"cc.SpriteFrame","content":{"name":"00000001","texture":"66u4n4WGFMRq+xitnAETaF","rect":[261,196,64,64],"offset":[0,0],"originalSize":[64,64]}},{"__type__":"cc.SpriteFrame","content":{"name":"10011111","texture":"66u4n4WGFMRq+xitnAETaF","rect":[66,196,64,64],"offset":[0,0],"originalSize":[64,64]}},{"__type__":"cc.SpriteFrame","content":{"name":"01101111","texture":"66u4n4WGFMRq+xitnAETaF","rect":[261,66,64,64],"offset":[0,0],"originalSize":[64,64]}},{"__type__":"cc.SpriteFrame","content":{"name":"11101001","texture":"66u4n4WGFMRq+xitnAETaF","rect":[66,66,64,64],"offset":[0,0],"originalSize":[64,64]}},{"__type__":"cc.SpriteFrame","content":{"name":"01101100","texture":"66u4n4WGFMRq+xitnAETaF","rect":[391,66,64,64],"offset":[0,0],"originalSize":[64,64]}},{"__type__":"cc.SpriteFrame","content":{"name":"11111100","texture":"66u4n4WGFMRq+xitnAETaF","rect":[1,131,64,64],"offset":[0,0],"originalSize":[64,64]}},{"__type__":"cc.SpriteFrame","content":{"name":"10010000","texture":"66u4n4WGFMRq+xitnAETaF","rect":[66,391,64,64],"offset":[0,0],"originalSize":[64,64]}},{"__type__":"cc.SpriteFrame","content":{"name":"11010110","texture":"66u4n4WGFMRq+xitnAETaF","rect":[326,1,64,64],"offset":[0,0],"originalSize":[64,64]}},{"__type__":"cc.SpriteFrame","content":{"name":"10010011","texture":"66u4n4WGFMRq+xitnAETaF","rect":[66,326,64,64],"offset":[0,0],"originalSize":[64,64]}},{"__type__":"cc.SpriteFrame","content":{"name":"11111110","texture":"66u4n4WGFMRq+xitnAETaF","rect":[1,66,64,64],"offset":[0,0],"originalSize":[64,64]}}]